{"schema":6,"addons":[{"id":"uBlock0@raymondhill.net","icons":{"32":"https://addons.mozilla.org/user-media/addon_icons/607/607454-32.png?modified=mcrushed","64":"https://addons.mozilla.org/user-media/addon_icons/607/607454-64.png?modified=mcrushed","128":"https://addons.mozilla.org/user-media/addon_icons/607/607454-128.png?modified=mcrushed"},"name":"uBlock Origin","version":"1.72.2","sourceURI":"https://addons.mozilla.org/firefox/downloads/file/4888680/ublock_origin-1.72.2.xpi","homepageURL":"https://github.com/gorhill/uBlock#ublock-origin","supportURL":"https://old.reddit.com/r/uBlockOrigin/","amoListingURL":"https://addons.mozilla.org/en-US/firefox/addon/ublock-origin/","description":"Finally, an efficient wide-spectrum content blocker. Easy on CPU and memory.","fullDescription":"uBlock Origin is not an \"ad blocker\", it's a wide-spectrum content blocker with CPU and memory efficiency as a primary feature.\n\n\n\nOut of the box, uBO blocks ads, trackers, coin miners, popups, etc. through the following lists of filters, enabled by default:\n\n    EasyList (ads)\n    EasyPrivacy (tracking)\n    Peter Lowe’s Ad server list (ads and tracking)\n    Online Malicious URL Blocklist\n    uBO's own lists\n\n\nMore lists are available for you to select if you wish:\n\n    EasyList Cookie\n    Fanboy Annoyances\n    AdGuard Annoyances\n    Dan Pollock’s hosts file\n    And many others\n\n\nAdditionally, you can point-and-click to block JavaScript locally or globally, create your own global or local rules to override entries from filter lists, and many more advanced features.\n\n\n\nFree.\nOpen source with public license (GPLv3)\nFor users by users.\n\nIf ever you really do want to contribute something, think about the people working hard to maintain the filter lists you are using, which were made available to use by all for free.\n\n\n    Documentation\n    Release notes\n    Community support @ Reddit\n    Contributors @ GitHub\n    Contributors @ Crowdin","weeklyDownloads":213633,"type":"extension","creator":{"name":"Raymond Hill","url":"https://addons.mozilla.org/en-US/firefox/user/11423598/"},"developers":[],"screenshots":[{"url":"https://addons.mozilla.org/user-media/previews/full/238/238546.png?modified=1622132421","width":1011,"height":758,"thumbnailURL":"https://addons.mozilla.org/user-media/previews/thumbs/238/238546.jpg?modified=1622132421","thumbnailWidth":533,"thumbnailHeight":400,"caption":"The popup panel: default mode"},{"url":"https://addons.mozilla.org/user-media/previews/full/238/238548.png?modified=1622132423","width":1011,"height":758,"thumbnailURL":"https://addons.mozilla.org/user-media/previews/thumbs/238/238548.jpg?modified=1622132423","thumbnailWidth":533,"thumbnailHeight":400,"caption":"The dashboard: stock filter lists"},{"url":"https://addons.mozilla.org/user-media/previews/full/238/238547.png?modified=1622132425","width":1011,"height":758,"thumbnailURL":"https://addons.mozilla.org/user-media/previews/thumbs/238/238547.jpg?modified=1622132425","thumbnailWidth":533,"thumbnailHeight":400,"caption":"The popup panel: default-deny mode"},{"url":"https://addons.mozilla.org/user-media/previews/full/238/238549.png?modified=1622132426","width":1011,"height":758,"thumbnailURL":"https://addons.mozilla.org/user-media/previews/thumbs/238/238549.jpg?modified=1622132426","thumbnailWidth":533,"thumbnailHeight":400,"caption":"The dashboard: settings"},{"url":"https://addons.mozilla.org/user-media/previews/full/238/238552.png?modified=1622132430","width":970,"height":1800,"thumbnailURL":"https://addons.mozilla.org/user-media/previews/thumbs/238/238552.jpg?modified=1622132430","thumbnailWidth":216,"thumbnailHeight":400,"caption":"The popup panel in Firefox Preview: default mode with more blocking options revealed"},{"url":"https://addons.mozilla.org/user-media/previews/full/230/230370.png?modified=1622132432","width":800,"height":600,"thumbnailURL":"https://addons.mozilla.org/user-media/previews/thumbs/230/230370.jpg?modified=1622132432","thumbnailWidth":533,"thumbnailHeight":400,"caption":"The unified logger tells you all that uBO is seeing and doing"}],"contributionURL":"","averageRating":4.8004,"reviewCount":5767,"reviewURL":"https://addons.mozilla.org/en-US/firefox/addon/ublock-origin/reviews/","updateDate":1783699276000},{"id":"1vpn@example.com","icons":{"32":"https://addons.mozilla.org/user-media/addon_icons/2802/2802483-32.png?modified=e258e562","64":"https://addons.mozilla.org/user-media/addon_icons/2802/2802483-64.png?modified=e258e562","128":"https://addons.mozilla.org/user-media/addon_icons/2802/2802483-128.png?modified=e258e562"},"name":"VPN","version":"4.1.4","sourceURI":"https://addons.mozilla.org/firefox/downloads/file/4814680/1vpn-4.1.4.xpi","homepageURL":"https://1vpn.org","supportURL":"https://1vpn.org","amoListingURL":"https://addons.mozilla.org/en-US/firefox/addon/1vpn/","description":"1VPN - Free VPN Proxy, Unlimited Data, Fast Speeds, Secure Encryption, No-Logs Policy, and Easy to Use.","fullDescription":"1VPN is a free VPN proxy browser extension that changes your IP address by routing your internet traffic through our secure servers.\n\n✨ Features ✨\n\n🆓 Free VPN – Enjoy secure, private internet browsing with our free VPN tier at no cost.\n\n📝 No Registration Required – Use the free VPN tier instantly without creating an account.\n\n🔒 Secure Encryption – Data is secured using SSL (TLS) encryption.\n\n❌ No-Logs Policy – Your browsing history, IP address, and personal data are never stored.\n\n♾️ Unlimited Bandwidth – No data caps on streaming, downloading, or browsing.\n\n⚡ Fast Speeds – Consistent and reliable VPN performance across all locations.\n\n🌐 Global Server Network – Access VPN servers in multiple countries for better speed and content access.\n\n🪶 Lightweight – Designed to be resource-efficient so it doesn’t slow down your browser.\n\n👍 Easy to Use – Simple, clean design that's easy for anyone to use.\n\n💬 Quick Support – Friendly and responsive support team available anytime.\n\n🗺️ Spoof Geolocation – Spoof HTML5 Geolocation API to match your current VPN location.\n\n📡 Disable WebRTC – Disable WebRTC to prevent your real IP address from leaking.\n\n\n\n🚀 Use Cases 🚀\n\n🛡️ Protect Your IP Address – Prevent tracking by hiding your IP address from websites, advertisers, and snoopers.\n\n🕵️‍♂️ Private Browsing – Keep your online activity hidden from ISPs and network administrators.\n\n🔑 Bypass Internet Censorship – Access blocked websites and apps on restricted networks or in censored regions.\n\n🌍 Unblock Region-Locked Content – Unlock websites and services not available in your country.\n\n\n\n🔗 Links 🔗\n\nPrivacy Policy – https://1vpn.org/privacy_policy\n\nTerms of Service – https://1vpn.org/terms_of_service\n\nTwitter – https://twitter.com/1VPNofficial\n\nReddit – https://www.reddit.com/r/1VPN\n\nGitHub – https://github.com/1vpn\n\n\n\n1VPN (also known as 1 VPN, One VPN, or OneVPN) is compatible with Manifest V3 (MV3) and strictly adheres to all Web Store policies and terms of service.","weeklyDownloads":25406,"type":"extension","creator":{"name":"1VPN","url":"https://addons.mozilla.org/en-US/firefox/user/17942470/"},"developers":[],"screenshots":[{"url":"https://addons.mozilla.org/user-media/previews/full/348/348449.png?modified=1768954494","width":1280,"height":800,"thumbnailURL":"https://addons.mozilla.org/user-media/previews/thumbs/348/348449.jpg?modified=1768954494","thumbnailWidth":533,"thumbnailHeight":333},{"url":"https://addons.mozilla.org/user-media/previews/full/348/348450.png?modified=1768954494","width":1280,"height":800,"thumbnailURL":"https://addons.mozilla.org/user-media/previews/thumbs/348/348450.jpg?modified=1768954494","thumbnailWidth":533,"thumbnailHeight":333},{"url":"https://addons.mozilla.org/user-media/previews/full/348/348451.png?modified=1768954494","width":1280,"height":800,"thumbnailURL":"https://addons.mozilla.org/user-media/previews/thumbs/348/348451.jpg?modified=1768954494","thumbnailWidth":533,"thumbnailHeight":333}],"contributionURL":"","averageRating":4.2377,"reviewCount":378,"reviewURL":"https://addons.mozilla.org/en-US/firefox/addon/1vpn/reviews/","updateDate":1779442830000},{"id":"{6bbdb3f9-6bd5-4385-9087-e293ec8d21a4}","icons":{"32":"https://addons.mozilla.org/static-server/img/addon-icons/default-32.png","64":"https://addons.mozilla.org/static-server/img/addon-icons/default-64.png","128":"https://addons.mozilla.org/static-server/img/addon-icons/default-128.png"},"name":"rose-pine","version":"1.0","sourceURI":"https://addons.mozilla.org/firefox/downloads/file/3847671/rose_pine-1.0.xpi","homepageURL":null,"supportURL":"https://devnity.pl","amoListingURL":"https://addons.mozilla.org/en-US/firefox/addon/rose-pine/","description":"Inspired by Rosé Pine (https://rosepinetheme.com/)","fullDescription":null,"weeklyDownloads":14,"type":"theme","creator":{"name":"jatne","url":"https://addons.mozilla.org/en-US/firefox/user/15915613/"},"developers":[],"screenshots":[{"url":"https://addons.mozilla.org/user-media/version-previews/full/3866/3866812.png?modified=1633077385","width":680,"height":92,"thumbnailURL":"https://addons.mozilla.org/user-media/version-previews/thumbs/3866/3866812.png?modified=1633077385","thumbnailWidth":473,"thumbnailHeight":64},{"url":"https://addons.mozilla.org/user-media/version-previews/full/3866/3866813.svg?modified=1633077385","width":720,"height":92,"thumbnailURL":"https://addons.mozilla.org/user-media/version-previews/thumbs/3866/3866813.jpg?modified=1633077385","thumbnailWidth":720,"thumbnailHeight":92}],"contributionURL":"","averageRating":4.75,"reviewCount":0,"reviewURL":"https://addons.mozilla.org/en-US/firefox/addon/rose-pine/reviews/","updateDate":1633083762000}]}